tuneflow/__init__.py
tuneflow/_about.py
tuneflow-0.0.1.dist-info/LICENSE
tuneflow-0.0.1.dist-info/METADATA
tuneflow-0.0.1.dist-info/WHEEL
tuneflow-0.0.1.dist-info/top_level.txt
tuneflow-0.0.1.dist-info/RECORD
